LICENSE.txt
MANIFEST.in
README.rst
setup.cfg
setup.py
data/data_file
dynamodb_stream_parser.egg-info/PKG-INFO
dynamodb_stream_parser.egg-info/SOURCES.txt
dynamodb_stream_parser.egg-info/dependency_links.txt
dynamodb_stream_parser.egg-info/entry_points.txt
dynamodb_stream_parser.egg-info/requires.txt
dynamodb_stream_parser.egg-info/top_level.txt
sample/__init__.py